app/__init__.py
app/test.py
app/test_energy_landscape_visualizing.py
app/test_energy_landscape_visualizing_1sp.py
app/statevisualization/__init__.py
app/statevisualization/statevis.py
app/test_bilayervisualization/__init__.py
app/test_bilayervisualization/bilayer_visual.py
app/test_eigenvector_visualization/__init__.py
app/test_eigenvector_visualization/test.py
app/topocharge/__init__.py
app/topocharge/topocharge.py
spinterface/__init__.py
spinterface/algorithms/__init__.py
spinterface/algorithms/spineapple/__init__.py
spinterface/algorithms/spineapple/gneb/__init__.py
spinterface/algorithms/spineapple/gneb/cneb2d.py
spinterface/algorithms/spineapple/minimizer/__init__.py
spinterface/algorithms/spineapple/minimizer/cbfgs.py
spinterface/algorithms/spineapple/minimizer/cnewton_2d.py
spinterface/algorithms/spineapple/modefollowing/__init__.py
spinterface/algorithms/spineapple/modefollowing/cmodefollowing_2d.py
spinterface/algorithms/spineapple/saddlepointsearch/__init__.py
spinterface/algorithms/spineapple/saddlepointsearch/csps_naive.py
spinterface/inputs/CWriteInputs.py
spinterface/inputs/__init__.py
spinterface/inputs/lattice/CCubicLattice.py
spinterface/inputs/lattice/CHexLattice.py
spinterface/inputs/lattice/CLattice.py
spinterface/inputs/lattice/CMagnetizations.py
spinterface/inputs/lattice/ILattice.py
spinterface/inputs/lattice/__init__.py
spinterface/inputs/lattice/const.py
spinterface/inputs/lattice/utilities.py
spinterface/inputs/lattice/modeconstruction/__init__.py
spinterface/inputs/lattice/modeconstruction/cconstructiontranslational.py
spinterface/inputs/lattice/modeconstruction/imodeconstruction.py
spinterface/inputs/lattice/spintransformations/CRotation.py
spinterface/inputs/lattice/spintransformations/__init__.py
spinterface/inputs/lattice/topology/CTopology.py
spinterface/inputs/lattice/topology/ITopology.py
spinterface/inputs/lattice/topology/__init__.py
spinterface/sps_results/CSPS.py
spinterface/sps_results/__init__.py
spinterface-0.0.71.dist-info/LICENSE
spinterface-0.0.71.dist-info/METADATA
spinterface-0.0.71.dist-info/WHEEL
spinterface-0.0.71.dist-info/top_level.txt
spinterface-0.0.71.dist-info/RECORD
