Metadata-Version: 2.1
Name: spinterface
Version: 0.0.71
Summary: An interface for dealing with the spindynamic program of spintronics theory group of the university of Kiel
Home-page: https://gitlab.com/hschrautzer/spinterface
Author: Hendrik Schrautzer
Author-email: hes93@hi.is
Classifier: Programming Language :: Python :: 3
Classifier: License :: OSI Approved :: MIT License
Classifier: Operating System :: OS Independent
Requires-Python: >=3.6
License-File: LICENSE
